solrcloudpy/__init__.py
solrcloudpy/collection/__init__.py
solrcloudpy/collection/admin.py
solrcloudpy/collection/data/__init__.py
solrcloudpy/collection/data/abstracts/__init__.py
solrcloudpy/collection/data/abstracts/abstract_document_model.py
solrcloudpy/collection/data/abstracts/abstract_document_update_model_dto.py
solrcloudpy/collection/data/enums/__init__.py
solrcloudpy/collection/data/enums/field_type_class.py
solrcloudpy/collection/data/models/__init__.py
solrcloudpy/collection/data/models/dto_utlils.py
solrcloudpy/collection/data/models/field_model_dto.py
solrcloudpy/collection/data/models/field_type_model_dto.py
solrcloudpy/collection/indexer.py
solrcloudpy/collection/schema.py
solrcloudpy/collection/search.py
solrcloudpy/collection/stats.py
solrcloudpy/connection.py
solrcloudpy/parameters.py
solrcloudpy/utils.py
solrcloudpy_typed-0.1.0.dist-info/LICENSE.txt
solrcloudpy_typed-0.1.0.dist-info/METADATA
solrcloudpy_typed-0.1.0.dist-info/WHEEL
solrcloudpy_typed-0.1.0.dist-info/RECORD
