Metadata-Version: 2.1
Name: solrcloudpy-typed
Version: 0.1.0
Summary: 
Author: Mehul Ahal
Author-email: m.ahal@dimerce.com
Requires-Python: >=3.11,<4.0
Classifier: Programming Language :: Python :: 3
Classifier: Programming Language :: Python :: 3.11
Classifier: Programming Language :: Python :: 3.12
Requires-Dist: future
Requires-Dist: ipython
Requires-Dist: pathlib2
Requires-Dist: requests
Requires-Dist: semver
